docfusion/__init__.py
docfusion/_version.py
docfusion_ai-0.1.1.dist-info/LICENSE.md
docfusion_ai-0.1.1.dist-info/METADATA
docfusion_ai-0.1.1.dist-info/WHEEL
docfusion_ai-0.1.1.dist-info/RECORD
