Metadata-Version: 2.1
Name: docfusion-ai
Version: 0.1.1
Summary: 
Author: adithya-s-k
Author-email: adithyaskolavi@gmail.com
Requires-Python: >=3.10,<3.13
Classifier: Programming Language :: Python :: 3
Classifier: Programming Language :: Python :: 3.10
Classifier: Programming Language :: Python :: 3.11
Classifier: Programming Language :: Python :: 3.12
Requires-Dist: doclayout-yolo (>=0.0.2,<0.0.3)
Requires-Dist: huggingface-hub (>=0.26.2,<0.27.0)
Requires-Dist: transformers (>=4.46.3,<5.0.0)
